bridge_mcp_ghidra.py
ghidramcp-0.0.dev0.dist-info/METADATA
ghidramcp-0.0.dev0.dist-info/WHEEL
ghidramcp-0.0.dev0.dist-info/entry_points.txt
ghidramcp-0.0.dev0.dist-info/licenses/LICENSE
ghidramcp-0.0.dev0.dist-info/RECORD
