Metadata-Version: 2.4
Name: ghidramcp
Version: 0.0.dev0
Summary: Model Context Protocol server for Ghidra reverse engineering
Project-URL: Homepage, https://github.com/LaurieWired/GhidraMCP
Project-URL: Repository, https://github.com/LaurieWired/GhidraMCP
Project-URL: Issues, https://github.com/LaurieWired/GhidraMCP/issues
Author: LaurieWired
License-Expression: Apache-2.0
License-File: LICENSE
Keywords: ghidra,mcp,model-context-protocol,reverse-engineering
Classifier: Development Status :: 4 - Beta
Classifier: Intended Audience :: Developers
Classifier: Programming Language :: Python :: 3
Classifier: Programming Language :: Python :: 3.10
Classifier: Programming Language :: Python :: 3.11
Classifier: Programming Language :: Python :: 3.12
Classifier: Programming Language :: Python :: 3.13
Classifier: Topic :: Software Development :: Disassemblers
Requires-Python: >=3.10
Requires-Dist: mcp<2,>=1.2.0
Requires-Dist: requests<3,>=2
